streamlit_deephaven/__init__.py
streamlit_deephaven/streamlit_deephaven.py
streamlit_deephaven-0.0.7.dist-info/LICENSE
streamlit_deephaven-0.0.7.dist-info/METADATA
streamlit_deephaven-0.0.7.dist-info/WHEEL
streamlit_deephaven-0.0.7.dist-info/top_level.txt
streamlit_deephaven-0.0.7.dist-info/RECORD
