Metadata-Version: 2.1
Name: streamlit-deephaven
Version: 0.0.7
Summary: Streamlit Deephaven Component
Home-page: https://github.com/deephaven/streamlit-deephaven
Author: Deephaven Data Labs
Author-email: support@deephaven.io
Requires-Python: >=3.6
License-File: LICENSE
Requires-Dist: streamlit >=0.63
Requires-Dist: deephaven-server >=0.23.0
